Perry
PerryFlask
