Metadata-Version: 2.1
Name: Perry
Version: 0.1.13
Summary:  A framework that let's you compose websites in Python with ease!   
Home-page: http://pypi.python.org/pypi/Perry/
Author: HUSKI3
Author-email: ignispy@protonmail.com
License: UNKNOWN
Project-URL: Bug Tracker, https://github.com/HUSKI3/Perry/issues
Platform: UNKNOWN
Classifier: Programming Language :: Python :: 3
Classifier: Operating System :: OS Independent
Requires-Python: >=3.6
